LICENSE.txt
MANIFEST.in
README.rst
requirements.txt
setup.py
pyemili/Lines.py
pyemili/Spec.py
pyemili/__init__.py
pyemili/numba_func.py
pyemili.egg-info/PKG-INFO
pyemili.egg-info/SOURCES.txt
pyemili.egg-info/dependency_links.txt
pyemili.egg-info/requires.txt
pyemili.egg-info/top_level.txt
pyemili/Line_dataset/Linedb.npz
pyemili/Line_dataset/base_lines.dat
pyemili/Line_dataset/elebin_index.npy
pyemili/Line_dataset/ioni_energy.npy
pyemili/Line_dataset/ionlevel.dat
pyemili/Line_dataset/match_lines.dat
pyemili/abundance/abun_WC.dat
pyemili/abundance/abun_nebula.dat
pyemili/abundance/abun_solar.dat
pyemili/eff_reccoe/CII_emiss_data.npy
pyemili/eff_reccoe/CII_emiss_lines.dat
pyemili/eff_reccoe/HI_emiss_data.npy
pyemili/eff_reccoe/HI_emiss_lines.dat
pyemili/eff_reccoe/HeII_emiss_data.npy
pyemili/eff_reccoe/HeII_emiss_lines.dat
pyemili/eff_reccoe/HeI_emiss_data.npy
pyemili/eff_reccoe/HeI_emiss_lines.dat
pyemili/eff_reccoe/NII_emiss_data.npy
pyemili/eff_reccoe/NII_emiss_lines.dat
pyemili/eff_reccoe/NeII_emiss_data.npy
pyemili/eff_reccoe/NeII_emiss_lines.dat
pyemili/eff_reccoe/OII_emiss_data.npy
pyemili/eff_reccoe/OII_emiss_lines.dat
pyemili/eff_reccoe/eff_Ne.npy
pyemili/eff_reccoe/eff_Te.npy
pyemili/recom/DR_rate.dat
pyemili/recom/RR_rate.dat