Metadata-Version: 2.1
Name: pyemili
Version: 1.0.1
Summary: Spectral lines identifier
Home-page: https://github.com/LuShenJ/PyEMILI
Author: Zhijun Tu, Xuan Fang, Robert Williams, Jifeng Liu
Author-email: zjtu@bao.ac.cn
License-File: LICENSE.txt
Requires-Dist: numpy
Requires-Dist: scipy
Requires-Dist: matplotlib
Requires-Dist: numba>=0.60.0
Requires-Dist: pandas>=2.0.3
Requires-Dist: astropy
Requires-Dist: tqdm
